LICENSE
MANIFEST.in
NOTICE
README.rst
VERSION
requirements.txt
setup.py
src/sagemaker_scikit_learn_extension.egg-info/PKG-INFO
src/sagemaker_scikit_learn_extension.egg-info/SOURCES.txt
src/sagemaker_scikit_learn_extension.egg-info/dependency_links.txt
src/sagemaker_scikit_learn_extension.egg-info/requires.txt
src/sagemaker_scikit_learn_extension.egg-info/top_level.txt
src/sagemaker_sklearn_extension/__init__.py
src/sagemaker_sklearn_extension/contrib/__init__.py
src/sagemaker_sklearn_extension/contrib/taei/__init__.py
src/sagemaker_sklearn_extension/contrib/taei/latent_space_oversampler.py
src/sagemaker_sklearn_extension/contrib/taei/models.py
src/sagemaker_sklearn_extension/contrib/taei/nn_utils.py
src/sagemaker_sklearn_extension/contrib/taei/star_oversampler.py
src/sagemaker_sklearn_extension/decomposition/__init__.py
src/sagemaker_sklearn_extension/decomposition/robust_pca.py
src/sagemaker_sklearn_extension/externals/__init__.py
src/sagemaker_sklearn_extension/externals/automl_transformer.py
src/sagemaker_sklearn_extension/externals/header.py
src/sagemaker_sklearn_extension/externals/read_data.py
src/sagemaker_sklearn_extension/feature_extraction/__init__.py
src/sagemaker_sklearn_extension/feature_extraction/date_time.py
src/sagemaker_sklearn_extension/feature_extraction/sequences.py
src/sagemaker_sklearn_extension/feature_extraction/text.py
src/sagemaker_sklearn_extension/impute/__init__.py
src/sagemaker_sklearn_extension/impute/base.py
src/sagemaker_sklearn_extension/preprocessing/__init__.py
src/sagemaker_sklearn_extension/preprocessing/base.py
src/sagemaker_sklearn_extension/preprocessing/data.py
src/sagemaker_sklearn_extension/preprocessing/encoders.py
test/test_automl_transformer.py
test/test_common.py
test/test_data.py
test/test_date_time.py
test/test_feature_extraction_text.py
test/test_header.py
test/test_impute.py
test/test_preprocessing.py
test/test_preprocessing_encoders.py
test/test_read_data.py
test/test_robust_pca.py
test/test_sequence_transformer.py