Metadata-Version: 2.1
Name: sagemaker-scikit-learn-extension
Version: 2.4.0
Summary: Open source library extension of scikit-learn for Amazon SageMaker.
Home-page: https://github.com/aws/sagemaker-scikit-learn-extension/
Author: Amazon Web Services
License: Apache License 2.0
Keywords: ML Amazon AWS AI SKLearn Scikit-Learn
Platform: UNKNOWN
Classifier: Development Status :: 4 - Beta
Classifier: License :: OSI Approved :: Apache Software License
Provides-Extra: test
Provides-Extra: taei
